LICENSE
MANIFEST.in
README.rst
setup.py
django_ptree_extra_views.egg-info/PKG-INFO
django_ptree_extra_views.egg-info/SOURCES.txt
django_ptree_extra_views.egg-info/dependency_links.txt
django_ptree_extra_views.egg-info/requires.txt
django_ptree_extra_views.egg-info/top_level.txt
extra_views/__init__.py
extra_views/advanced.py
extra_views/formsets.py
extra_views/models.py
extra_views/views.py
extra_views/tests/__init__.py
extra_views/tests/forms.py
extra_views/tests/formsets.py
extra_views/tests/models.py
extra_views/tests/tests.py
extra_views/tests/urls.py
extra_views/tests/views.py
extra_views/tests/templates/404.html
extra_views/tests/templates/extra_views/address_formset.html
extra_views/tests/templates/extra_views/event_calendar_month.html
extra_views/tests/templates/extra_views/formsets_multiview.html
extra_views/tests/templates/extra_views/inline_formset.html
extra_views/tests/templates/extra_views/item_formset.html
extra_views/tests/templates/extra_views/item_list.html
extra_views/tests/templates/extra_views/order_and_items.html
extra_views/tests/templates/extra_views/orderaddress_multiview.html
extra_views/tests/templates/extra_views/orderitems_multiview.html
extra_views/tests/templates/extra_views/paged_formset.html
extra_views/tests/templates/extra_views/sortable_item_list.html
extra_views/tests/templates/extra_views/success.html