Metadata-Version: 1.1
Name: django-ptree-extra-views
Version: 0.6.3
Summary: Extra class-based views for Django
Home-page: https://github.com/AndrewIngram/django-extra-views
Author: Andrew Ingram
Author-email: andy@andrewingram.net
License: MIT
Platform: UNKNOWN
Classifier: Development Status :: 3 - Alpha
Classifier: Environment :: Web Environment
Classifier: Framework :: Django
Classifier: Intended Audience :: Developers
Classifier: Programming Language :: Python
